polyserde/__init__.py
polyserde/polyserde.py
polyserde-0.1.1.dist-info/WHEEL
polyserde-0.1.1.dist-info/METADATA
polyserde-0.1.1.dist-info/RECORD
