Metadata-Version: 2.3
Name: polyserde
Version: 0.1.1
Summary: Polymorphic serialization / deserialization for pydantic data classes
Keywords: pydantic,serialization,deserialization,polymorphic,json,configuration
Author: Janos Tolgyesi
Classifier: Development Status :: 4 - Beta
Classifier: Intended Audience :: Developers
Classifier: License :: OSI Approved :: MIT License
Classifier: Programming Language :: Python :: 3
Classifier: Programming Language :: Python :: 3.9
Classifier: Programming Language :: Python :: 3.10
Classifier: Programming Language :: Python :: 3.11
Classifier: Programming Language :: Python :: 3.12
Classifier: Programming Language :: Python :: 3.13
Classifier: Topic :: Software Development :: Libraries :: Python Modules
Classifier: Topic :: Software Development :: Object Brokering
Classifier: Typing :: Typed
Requires-Dist: packaging>=25.0,<=26.0
Requires-Dist: pydantic>=2.0.0,<3.0.0
Requires-Dist: pytest>=7.0.0 ; extra == 'dev'
Requires-Python: >=3.9
Project-URL: Bug Tracker, https://github.com/mrtj/polyserde/issues
Project-URL: Documentation, https://github.com/mrtj/polyserde#readme
Project-URL: Homepage, https://github.com/mrtj/polyserde
Project-URL: Repository, https://github.com/mrtj/polyserde
Provides-Extra: dev
